taichu_serve/__init__.py
taichu_serve/app.py
taichu_serve/command.py
taichu_serve/common.py
taichu_serve/dockerfile.py
taichu_serve/error_code.py
taichu_serve/grpc_predict_v2_pb2.py
taichu_serve/grpc_predict_v2_pb2_grpc.py
taichu_serve/grpc_server.py
taichu_serve/log.py
taichu_serve/model_server.py
taichu_serve/ratelimiter.py
taichu_serve/settings.py
taichu_serve/template/__init__.py
taichu_serve/template/model_service.py
taichu_serve/template/test/__init__.py
taichu_serve/template/test/grpc_client.py
taichu_serve/template/test/http_client.py
taichu_serve/template/test/stream_grpc_client.py
taichu_serve/third/__init__.py
taichu_serve/third/tracer.py
taichu_serve-2.0.32.dist-info/METADATA
taichu_serve-2.0.32.dist-info/WHEEL
taichu_serve-2.0.32.dist-info/entry_points.txt
taichu_serve-2.0.32.dist-info/top_level.txt
taichu_serve-2.0.32.dist-info/RECORD
