Metadata-Version: 2.1
Name: taichu-serve
Version: 2.0.32
Summary: taichu serve is a tool for serving deep learning inference
Home-page: 
Author: taichu platform team
Keywords: Serving Deep Learning Inference AI
Requires-Python: >=3.6.0
Requires-Dist: grpcio
Requires-Dist: grpcio-tools
Requires-Dist: protobuf
Requires-Dist: Flask
Requires-Dist: gunicorn
Requires-Dist: requests
Requires-Dist: opentelemetry-api
Requires-Dist: opentelemetry-sdk
Requires-Dist: opentelemetry-exporter-otlp
Requires-Dist: opentelemetry-instrumentation-flask
Requires-Dist: opentelemetry-instrumentation-grpc
